{
    "param_features": {
        "previous": "CPU,RAM,response_time,cpu_rolling_mean,ram_rolling_mean,response_rolling_mean,high_cpu,high_ram,is_peak_hour",
        "current": [
            "CPU",
            "RAM",
            "response_time",
            "cpu_rolling_mean",
            "ram_rolling_mean",
            "response_rolling_mean",
            "high_cpu",
            "high_ram",
            "is_peak_hour"
        ]
    },
    "metric_accuracy": {
        "previous": null,
        "current": 0.8109171379395131,
        "improved": null
    },
    "metric_precision": {
        "previous": null,
        "current": 0.7991160220994475,
        "improved": null
    },
    "metric_recall": {
        "previous": null,
        "current": 0.8518256772673733,
        "improved": null
    },
    "metric_f1_score": {
        "previous": null,
        "current": 0.8246294184720638,
        "improved": null
    }
}